dictionary/__init__.py
dictionary/dictionary.py
holy_dictionary-2.0.0.dist-info/METADATA
holy_dictionary-2.0.0.dist-info/WHEEL
holy_dictionary-2.0.0.dist-info/top_level.txt
holy_dictionary-2.0.0.dist-info/RECORD
